acalib/__init__.py
acalib/algorithms/__init__.py
acalib/algorithms/algorithm.py
acalib/algorithms/clumpFind.py
acalib/algorithms/fellWalker.py
acalib/algorithms/gms.py
acalib/algorithms/roise.py
acalib/algorithms/stacking.py
acalib/algorithms/attic/__init__.py
acalib/algorithms/attic/fellWalker2.py
acalib/algorithms/attic/gaussClumps.py
acalib/core/__init__.py
acalib/core/analysis.py
acalib/core/models.py
acalib/core/transform.py
acalib/core/utils.py
acalib/core/_morph/__init__.py
acalib/core/_morph/morph.cpython-36m-x86_64-linux-gnu.so
acalib/core/_morph/morph.so
acalib/core/_morph/setup.py
acalib/io/__init__.py
acalib/io/container.py
acalib/io/fits.py
acalib/io/graph.py
acalib/synthetic/__init__.py
acalib/synthetic/convert.py
acalib/synthetic/db.py
acalib/synthetic/dbcreator.py
acalib/synthetic/imc.py
acalib/synthetic/vu.py
acalib/upi/__init__.py
acalib/upi/axes.py
acalib/upi/flux.py
acalib/upi/formatting.py
acalib/upi/reduction.py
acalib-0.1.3.dist-info/DESCRIPTION.rst
acalib-0.1.3.dist-info/METADATA
acalib-0.1.3.dist-info/RECORD
acalib-0.1.3.dist-info/WHEEL
acalib-0.1.3.dist-info/metadata.json
acalib-0.1.3.dist-info/top_level.txt
