Metadata-Version: 2.0
Name: acalib
Version: 0.1.3
Summary: Advanced Computing for Astronomy Library
Home-page: https://github.com/ChileanVirtualObservatory/ACALIB
Author: CSRG
Author-email: contact@lirae.cl
License: UNKNOWN
Platform: UNKNOWN
Classifier: Intended Audience :: Science/Research
Classifier: Topic :: Scientific/Engineering :: Astronomy
Classifier: Programming Language :: Python :: 2.7
Classifier: Programming Language :: Python :: 3.6
Requires-Dist: astropy (>=1.2)
Requires-Dist: cython (>=0.18)
Requires-Dist: dask
Requires-Dist: distributed
Requires-Dist: matplotlib (>=1.5)
Requires-Dist: numpy (>=1.11.2)
Requires-Dist: pycupid
Requires-Dist: scikit-image (>=0.13)
Requires-Dist: scipy (>=0.18)
Requires-Dist: urllib3
